{
  "project_info": {
    "project_number": "483388838623",
    "firebase_url": "https://pharmacy-sos.firebaseio.com",
    "project_id": "pharmacy-sos",
    "storage_bucket": "pharmacy-sos.appspot.com"
  },
  "client": [
    {
      "client_info": {
        "mobilesdk_app_id": "1:483388838623:android:ca29d0eb863f69d8",
        "android_client_info": {
          "package_name": "com.psos"
        }
      },
      "oauth_client": [
        {
          "client_id": "483388838623-ts2dqfvkhjk89htn1if5dg0nkpiqcp59.apps.googleusercontent.com",
          "client_type": 3
        }
      ],
      "api_key": [
        {
          "current_key": "AIzaSyDW68vKRzowZaHLAaoJ6PTnReeC8ZcP5XA"
        }
      ],
      "services": {
        "appinvite_service": {
          "other_platform_oauth_client": [
            {
              "client_id": "483388838623-ts2dqfvkhjk89htn1if5dg0nkpiqcp59.apps.googleusercontent.com",
              "client_type": 3
            }
          ]
        }
      }
    }
  ],
  "configuration_version": "1"
}